rtl/controlunit.sv
module controlunit #(
    parameter DATA_WIDTH = 32
) (
    input logic [DATA_WIDTH-1:0] instr,  // Instruction input
    input logic                 EQ,     // Equality flag (for branch comparison)
    output logic [2:0]          ALUctrl, // ALU control signal
    output logic                ALUsrc,  // ALU source (1 for immediate, 0 for register)
    output logic [2:0]          ImmSrc,  // Immediate source selection
    output logic                PCsrc,   // Program counter source (for branches and jumps)
    output logic                RegWrite // Register write enable
);

    // Extract instruction fields
    logic [6:0] op;
    logic [2:0] funct3;
    logic [6:0] funct7;

    assign op = instr[6:0];
    assign funct3 = instr[14:12];
    assign funct7 = instr[31:25];

    always_comb begin
        // Default values
        ALUctrl = 3'b000;
        ALUsrc = 1'b0;
        ImmSrc = 3'b000;
        PCsrc = 1'b0;
        RegWrite = 1'b0;

        case (op)
            // R-Type
            7'b0110011: begin 
                case (funct3)
                    3'b000: ALUctrl = (funct7 == 7'b0100000) ? 3'b001 : 3'b000; // SUB/ADD
                    3'b110: ALUctrl = 3'b011; // OR
                    3'b111: ALUctrl = 3'b010; // AND
                    3'b010: ALUctrl = 3'b101; // SLT
                    default: ALUctrl = 3'b000;
                endcase
                RegWrite = 1'b1;
                ALUsrc = 1'b0;
            end

            // I-Type (Arithmetic)
            7'b0010011: begin 
                case (funct3)
                    3'b000: ALUctrl = 3'b000; // ADDI
                    3'b110: ALUctrl = 3'b011; // ORI
                    3'b111: ALUctrl = 3'b010; // ANDI
                    3'b010: ALUctrl = 3'b101; // SLTI
                    default: ALUctrl = 3'b000;
                endcase
                RegWrite = 1'b1;
                ALUsrc = 1'b1;
                ImmSrc = 3'b000;
            end

            // Load (I-Type)
            7'b0000011: begin 
                ALUctrl = 3'b000; // ADD for address calculation
                RegWrite = 1'b1;
                ALUsrc = 1'b1;
                ImmSrc = 3'b000;
            end

            // Store (S-Type)
            7'b0100011: begin 
                ALUctrl = 3'b000; // ADD for address calculation
                ALUsrc = 1'b0; // Uses rd2
                ImmSrc = 3'b001; // S-Type immediate
            end

            // Branch (B-Type)
            7'b1100011: begin 
                ALUctrl = 3'b001; // SUB for comparison
                ImmSrc = 3'b010; // B-Type immediate
                case (funct3)
                    3'b000: PCsrc = EQ ? 1'b1 : 1'b0; // BEQ
                    3'b001: PCsrc = EQ ? 1'b0 : 1'b1; // BNE
                    default: PCsrc = 1'b0;
                endcase
            end

            // J-Type (JAL)
            7'b1101111: begin 
                PCsrc = 1'b1;
                RegWrite = 1'b1;
                ALUsrc = 1'b1;
                ImmSrc = 3'b100;
            end

            // JALR (I-Type)
            7'b1100111: begin 
                PCsrc = 1'b1;
                RegWrite = 1'b1;
                ALUsrc = 1'b1;
                ImmSrc = 3'b000;
            end

            // LUI (Load Upper Immediate)
            7'b0110111: begin 
                RegWrite = 1'b1;
                ALUsrc = 1'b1;
                ImmSrc = 3'b011;
            end

            // AUIPC (Add Upper Immediate to PC)
            7'b0010111: begin 
                RegWrite = 1'b1;
                ALUsrc = 1'b1;
                ImmSrc = 3'b011;
            end

            // I-Type (ecall, ebreak)
            7'b1110011: begin 
                ALUsrc = 1'b1;
                if (funct3 == 3'b000) begin
                    RegWrite = 1'b0; // ecall/ebreak
                end else begin
                    RegWrite = 1'b1; // Other I-Type
                end
            end

            // Default case (unknown opcode)
            default: begin
                ALUctrl = 3'b000;
                ALUsrc = 1'b0;
                ImmSrc = 3'b000;
                PCsrc = 1'b0;
                RegWrite = 1'b0;
            end
        endcase
    end
endmodule

alu.sv
module ALU (
    input  logic [31:0] ALUop1,    
    input  logic [31:0] ALUop2,    
    input  logic [2:0] ALUctrl,    
    output logic [31:0] Result,    
    output logic EQ                
);

    always_comb begin
        Result = 32'b0;
        EQ = 0;

        case (ALUctrl)
            3'b000: Result = ALUop1 + ALUop2; // ADD (used in addi)
            3'b001: begin                     // SUB (used in bne)
                Result = ALUop1 - ALUop2;
                EQ = (Result == 0);           // Set EQ flag if ALUop1 == ALUop2
            end
            default: Result = 32'b0;    
        endcase
    end
endmodule

rtl/mux.sv
module mux #(
    DATA_WIDTH =32
)(
    input logic [DATA_WIDTH-1:0] in0,
    input logic [DATA_WIDTH-1:0] in1,
    input logic                  sel,
    output logic [DATA_WIDTH-1:0] out
);

    assign out = sel ? in1 : in0;

endmodule

rtl/registerfile.sv
module registerfile (
    input  logic        clk,
    input  logic        rst,     // Add reset signal
    input  logic        WE3,     // Write enable
    input  logic [4:0]  AD1,     // Read register 1 address
    input  logic [4:0]  AD2,     // Read register 2 address
    input  logic [4:0]  AD3,     // Write register address
    input  logic [31:0] WD3,     // Write data
    output logic [31:0] RD1,     // Read data 1
    output logic [31:0] RD2,     // Read data 2
    output logic [31:0] a0
);

    logic [31:0] registers [31:0];

    assign a0 = registers[10];

    // Initialize registers
    initial begin
        for (int i = 0; i < 32; i = i + 1)
            registers[i] = 32'h0;
    end

    // Synchronous write with reset
    always_ff @(posedge clk) begin
        if (rst) begin
            // Clear all registers on reset
            for (int i = 0; i < 32; i = i + 1)
                registers[i] <= 32'h0;
        end
        else if (WE3 && (AD3 != 5'b0)) begin // Don't write to x0
            registers[AD3] <= WD3;
        end
    end

    // Asynchronous read
    assign RD1 = (AD1 == 5'b0) ? 32'h0 : registers[AD1];
    assign RD2 = (AD2 == 5'b0) ? 32'h0 : registers[AD2];

    assign a0 = registers[10];

endmodule

rtl/signextension.sv
module signextension #(
    parameter DATA_WIDTH = 32
)(
    input  logic [31:0] instr,           // I-type immediate field
    input  logic  [2:0] ImmSrc,          // Immediate source select
    output logic [DATA_WIDTH-1:0] ImmOp  // Sign-extended output
);

    always_comb begin
        case (ImmSrc)
            3'b000: ImmOp = {{20{instr[31]}}, instr[31:20]};                                        //I type instruction
            3'b001: ImmOp = {{20{instr[31]}}, instr[31:25], instr[11:7]};                           //S type instruction
            3'b010: ImmOp = {{20{instr[31]}}, instr[7], instr[30:25], instr[11:8], 1'b0};           //B type instruction
            3'b011: ImmOp = {instr[31:12], 12'b0};                                                  //U type instruction
            3'b100: ImmOp = {{12{instr[31]}}, instr[31], instr[19:12], instr[20],instr[30:21],1'b0};//J type instruction
            default: ImmOp = {{20{instr[31]}}, instr[31:20]};
        // Sign extend the immediate value
        endcase
        
        // Debug print
        //$display("Sign Extension: Input = %h, Output = %h", instr, ImmOp);
    end

endmodule

rtl/instr_mem.sv
module instr_mem #(
    parameter   ADDRESS_WIDTH = 32,
                ADDRESS_REAL_WIDTH = 12,
                DATA_WIDTH = 8,
                DATA_OUT_WIDTH = 32
) (
    input logic [ADDRESS_WIDTH-1:0] addr,
    output logic [DATA_OUT_WIDTH-1:0] instr
);

// logic [ADDRESS_REAL_WIDTH:0] address [ADDRESS_REAL_WIDTH:0];

logic [DATA_WIDTH-1:0] array [2**ADDRESS_REAL_WIDTH-1:0];

initial begin
    $display("Loading program into instruction memory...");
    $readmemh("../rtl/program.hex", array);
end

// Put the 4 bytes back together to a 32-bit word
assign instr = {array[addr+3], array[addr+2], array[addr+1], array[addr]};

endmodule

rtl/program_counter.sv
module program_counter #(
    parameter WIDTH = 32
)(
    input  logic                 clk,
    input  logic                 rst,
    input  logic                 PCsrc,
    input  logic [WIDTH-1:0]     ImmOp,
    output logic [WIDTH-1:0]     PC
);

    always_ff @(posedge clk) begin
        if (rst) begin
            PC <= 32'h0;
        end else begin
            if (PCsrc)
                PC <= PC + ImmOp;  // Branch/Jump
            else
                PC <= PC + 32'd4;  // Normal increment
        end
    end

endmodule

rtl/top.sv
/* verilator lint_off SYNCASYNCNET */
module top (
    input logic clk,          // Clock signal
    input logic rst,          // Reset signal
    output logic [31:0] a0    // Contents of register a0 (output)
);

    // Internal Signals
    logic [31:0] PC;                      // Program Counter
    logic [31:0] instr;                   // Current instruction
    logic [31:0] ImmOp;                   // Sign-extended immediate value
    logic [31:0] ALUop1, ALUop2, ALUout;  // ALU operands and result
    logic EQ;                             // Equality output from ALU
    logic [31:0] RD2, WD3;                // Register file read/write data
    logic RegWrite, ALUsrc, PCsrc;        // Control signals
    logic [2:0] ImmSrc;                   // 2-bit Immediate source signal
    logic [2:0] ALUctrl;                  // ALU control signal

    // Program Counter
    program_counter #(.WIDTH(32)) PC_Reg (
        .clk(clk),
        .rst(rst),
        .PCsrc(PCsrc),
        .ImmOp(ImmOp),
        .PC(PC)
    );

    // Instruction Memory (asynchronous read)
    /*rom #(
        .ADDRESS_WIDTH(32),
        .DATA_WIDTH(8)
    ) InstructionMemory (
        .addr(PC),
        .instr(instr)
    );*/

    // Instruction Memory 2.0 
    instr_mem #(
        .ADDRESS_WIDTH(32),
        .ADDRESS_REAL_WIDTH(12),
        .DATA_WIDTH(8),
        .DATA_OUT_WIDTH(32)
    ) InstructionMemory (
        .addr(PC),
        .instr(instr)
    );

    // Sign Extension Unit
    signextension #(
        .DATA_WIDTH(32)
    ) SignExtender (
        .instr(instr),
        .ImmSrc(ImmSrc),
        .ImmOp(ImmOp)
    );

    // Register File with reset
    registerfile RegFile (
        .clk(clk),
        .rst(rst),
        .WE3(RegWrite),
        .AD1(instr[19:15]),
        .AD2(instr[24:20]),
        .AD3(instr[11:7]),
        .WD3(WD3),
        .RD1(ALUop1),
        .RD2(RD2),
        .a0(a0)
    );

    // ALU Operand MUX
    mux #(.DATA_WIDTH(32)) ALUOperandMux (
        .in0(RD2),
        .in1(ImmOp),
        .sel(ALUsrc),
        .out(ALUop2)
    );

    // ALU
    alu ArithmeticLogicUnit (
        .ALUop1(ALUop1),
        .ALUop2(ALUop2),
        .ALUctrl(ALUctrl),
        .Result(ALUout),
        .EQ(EQ)
    );

    // Control Unit
    controlunit controlunit (
        .instr(instr),
        .EQ(EQ),
        .RegWrite(RegWrite),
        .ALUsrc(ALUsrc),
        .ImmSrc(ImmSrc),
        .PCsrc(PCsrc),
        .ALUctrl(ALUctrl)
    );

    // Write back
    assign WD3 = ALUout;

endmodule
/* verilator lint_on SYNCASYNCNET */

tb/waveform.vcd
$version Generated by VerilatedVcd $end
$date Mon Dec  2 14:15:20 2024 $end
$timescale 1ps $end

 $scope module TOP $end
  $var wire 32 Z a0 [31:0] $end
  $var wire  1 X clk $end
  $var wire  1 Y rst $end
  $scope module top $end
   $var wire  3 0 ALUctrl [2:0] $end
   $var wire 32 ' ALUop1 [31:0] $end
   $var wire 32 ( ALUop2 [31:0] $end
   $var wire 32 ) ALUout [31:0] $end
   $var wire  1 - ALUsrc $end
   $var wire  1 * EQ $end
   $var wire 32 & ImmOp [31:0] $end
   $var wire  3 / ImmSrc [2:0] $end
   $var wire 32 $ PC [31:0] $end
   $var wire  1 . PCsrc $end
   $var wire 32 + RD2 [31:0] $end
   $var wire  1 , RegWrite $end
   $var wire 32 ) WD3 [31:0] $end
   $var wire 32 Z a0 [31:0] $end
   $var wire  1 X clk $end
   $var wire 32 % instr [31:0] $end
   $var wire  1 Y rst $end
   $scope module ALUOperandMux $end
    $var wire 32 [ DATA_WIDTH [31:0] $end
    $var wire 32 + in0 [31:0] $end
    $var wire 32 & in1 [31:0] $end
    $var wire 32 ( out [31:0] $end
    $var wire  1 - sel $end
   $upscope $end
   $scope module ArithmeticLogicUnit $end
    $var wire  3 0 ALUctrl [2:0] $end
    $var wire 32 ' ALUop1 [31:0] $end
    $var wire 32 ( ALUop2 [31:0] $end
    $var wire  1 * EQ $end
    $var wire 32 ) Result [31:0] $end
   $upscope $end
   $scope module InstructionMemory $end
    $var wire 32 \ ADDRESS_REAL_WIDTH [31:0] $end
    $var wire 32 [ ADDRESS_WIDTH [31:0] $end
    $var wire 32 [ DATA_OUT_WIDTH [31:0] $end
    $var wire 32 ] DATA_WIDTH [31:0] $end
    $var wire 32 $ addr [31:0] $end
    $var wire 32 % instr [31:0] $end
   $upscope $end
   $scope module PC_Reg $end
    $var wire 32 & ImmOp [31:0] $end
    $var wire 32 $ PC [31:0] $end
    $var wire  1 . PCsrc $end
    $var wire 32 [ WIDTH [31:0] $end
    $var wire  1 X clk $end
    $var wire  1 Y rst $end
   $upscope $end
   $scope module RegFile $end
    $var wire  5 1 AD1 [4:0] $end
    $var wire  5 2 AD2 [4:0] $end
    $var wire  5 3 AD3 [4:0] $end
    $var wire 32 ' RD1 [31:0] $end
    $var wire 32 + RD2 [31:0] $end
    $var wire 32 ) WD3 [31:0] $end
    $var wire  1 , WE3 $end
    $var wire 32 Z a0 [31:0] $end
    $var wire  1 X clk $end
    $var wire 32 4 registers[0] [31:0] $end
    $var wire 32 > registers[10] [31:0] $end
    $var wire 32 ? registers[11] [31:0] $end
    $var wire 32 @ registers[12] [31:0] $end
    $var wire 32 A registers[13] [31:0] $end
    $var wire 32 B registers[14] [31:0] $end
    $var wire 32 C registers[15] [31:0] $end
    $var wire 32 D registers[16] [31:0] $end
    $var wire 32 E registers[17] [31:0] $end
    $var wire 32 F registers[18] [31:0] $end
    $var wire 32 G registers[19] [31:0] $end
    $var wire 32 5 registers[1] [31:0] $end
    $var wire 32 H registers[20] [31:0] $end
    $var wire 32 I registers[21] [31:0] $end
    $var wire 32 J registers[22] [31:0] $end
    $var wire 32 K registers[23] [31:0] $end
    $var wire 32 L registers[24] [31:0] $end
    $var wire 32 M registers[25] [31:0] $end
    $var wire 32 N registers[26] [31:0] $end
    $var wire 32 O registers[27] [31:0] $end
    $var wire 32 P registers[28] [31:0] $end
    $var wire 32 Q registers[29] [31:0] $end
    $var wire 32 6 registers[2] [31:0] $end
    $var wire 32 R registers[30] [31:0] $end
    $var wire 32 S registers[31] [31:0] $end
    $var wire 32 7 registers[3] [31:0] $end
    $var wire 32 8 registers[4] [31:0] $end
    $var wire 32 9 registers[5] [31:0] $end
    $var wire 32 : registers[6] [31:0] $end
    $var wire 32 ; registers[7] [31:0] $end
    $var wire 32 < registers[8] [31:0] $end
    $var wire 32 = registers[9] [31:0] $end
    $var wire  1 Y rst $end
    $scope module unnamedblk1 $end
     $var wire 32 # i [31:0] $end
    $upscope $end
    $scope module unnamedblk2 $end
     $var wire 32 T i [31:0] $end
    $upscope $end
   $upscope $end
   $scope module SignExtender $end
    $var wire 32 [ DATA_WIDTH [31:0] $end
    $var wire 32 & ImmOp [31:0] $end
    $var wire  3 / ImmSrc [2:0] $end
    $var wire 32 % instr [31:0] $end
   $upscope $end
   $scope module controlunit $end
    $var wire  3 0 ALUctrl [2:0] $end
    $var wire  1 - ALUsrc $end
    $var wire 32 [ DATA_WIDTH [31:0] $end
    $var wire  1 * EQ $end
    $var wire  3 / ImmSrc [2:0] $end
    $var wire  1 . PCsrc $end
    $var wire  1 , RegWrite $end
    $var wire  3 V funct3 [2:0] $end
    $var wire  7 W funct7 [6:0] $end
    $var wire 32 % instr [31:0] $end
    $var wire  7 U op [6:0] $end
   $upscope $end
  $upscope $end
 $upscope $end
$enddefinitions $end


#1552
b00000000000000000000000000100000 #
b00000000000000000000000000000000 $
b00001111111100000000001100010011 %
b00000000000000000000000011111111 &
b00000000000000000000000000000000 '
b00000000000000000000000011111111 (
b00000000000000000000000011111111 )
0*
b00000000000000000000000000000000 +
1,
1-
0.
b000 /
b000 0
b00000 1
b11111 2
b00110 3
b00000000000000000000000000000000 4
b00000000000000000000000000000000 5
b00000000000000000000000000000000 6
b00000000000000000000000000000000 7
b00000000000000000000000000000000 8
b00000000000000000000000000000000 9
b00000000000000000000000000000000 :
b00000000000000000000000000000000 ;
b00000000000000000000000000000000 <
b00000000000000000000000000000000 =
b00000000000000000000000000000000 >
b00000000000000000000000000000000 ?
b00000000000000000000000000000000 @
b00000000000000000000000000000000 A
b00000000000000000000000000000000 B
b00000000000000000000000000000000 C
b00000000000000000000000000000000 D
b00000000000000000000000000000000 E
b00000000000000000000000000000000 F
b00000000000000000000000000000000 G
b00000000000000000000000000000000 H
b00000000000000000000000000000000 I
b00000000000000000000000000000000 J
b00000000000000000000000000000000 K
b00000000000000000000000000000000 L
b00000000000000000000000000000000 M
b00000000000000000000000000000000 N
b00000000000000000000000000000000 O
b00000000000000000000000000000000 P
b00000000000000000000000000000000 Q
b00000000000000000000000000000000 R
b00000000000000000000000000000000 S
b00000000000000000000000000000000 T
b0010011 U
b000 V
b0000111 W
1X
0Y
b00000000000000000000000000000000 Z
b00000000000000000000000000100000 [
b00000000000000000000000000001100 \
b00000000000000000000000000001000 ]
#1553
0X
#1554
b00000000000000000000000000000100 $
b00000000000000000000010100010011 %
b00000000000000000000000000000000 &
b00000000000000000000000000000000 (
b00000000000000000000000000000000 )
1*
b00000 2
b01010 3
b00000000000000000000000011111111 :
b0000000 W
1X
#1555
0X
#1556
b00000000000000000000000000001000 $
b00000000000000000000010110010011 %
b01011 3
1X
#1557
0X
#1558
b00000000000000000000000000001100 $
b00000000000001011000010100010011 %
b01011 1
b01010 3
1X
#1559
0X
#1560
b00000000000000000000000000010000 $
b00000000000101011000010110010011 %
b00000000000000000000000000000001 &
b00000000000000000000000000000001 (
b00000000000000000000000000000001 )
0*
b00001 2
b01011 3
1X
#1561
0X
#1562
b00000000000000000000000000010100 $
b11111110011001011001110011100011 %
b11111111111111111111111111111000 &
b00000000000000000000000000000001 '
b00000000000000000000000011111111 (
b11111111111111111111111100000010 )
b00000000000000000000000011111111 +
0,
0-
1.
b010 /
b001 0
b00110 2
b11001 3
b00000000000000000000000000000001 ?
b1100011 U
b001 V
b1111111 W
1X
#1563
0X
#1564
b00000000000000000000000000001100 $
b00000000000001011000010100010011 %
b00000000000000000000000000000000 &
b00000000000000000000000000000000 (
b00000000000000000000000000000001 )
b00000000000000000000000000000000 +
1,
1-
0.
b000 /
b000 0
b00000 2
b01010 3
b0010011 U
b000 V
b0000000 W
1X
#1565
0X
#1566
b00000000000000000000000000010000 $
b00000000000101011000010110010011 %
b00000000000000000000000000000001 &
b00000000000000000000000000000001 (
b00000000000000000000000000000010 )
b00001 2
b01011 3
b00000000000000000000000000000001 >
1X
b00000000000000000000000000000001 Z
#1567
0X
#1568
b00000000000000000000000000010100 $
b11111110011001011001110011100011 %
b11111111111111111111111111111000 &
b00000000000000000000000000000010 '
b00000000000000000000000011111111 (
b11111111111111111111111100000011 )
b00000000000000000000000011111111 +
0,
0-
1.
b010 /
b001 0
b00110 2
b11001 3
b00000000000000000000000000000010 ?
b1100011 U
b001 V
b1111111 W
1X
#1569
0X
#1570
b00000000000000000000000000001100 $
b00000000000001011000010100010011 %
b00000000000000000000000000000000 &
b00000000000000000000000000000000 (
b00000000000000000000000000000010 )
b00000000000000000000000000000000 +
1,
1-
0.
b000 /
b000 0
b00000 2
b01010 3
b0010011 U
b000 V
b0000000 W
1X
#1571
0X
#1572
b00000000000000000000000000010000 $
b00000000000101011000010110010011 %
b00000000000000000000000000000001 &
b00000000000000000000000000000001 (
b00000000000000000000000000000011 )
b00001 2
b01011 3
b00000000000000000000000000000010 >
1X
b00000000000000000000000000000010 Z
#1573
0X
#1574
b00000000000000000000000000010100 $
b11111110011001011001110011100011 %
b11111111111111111111111111111000 &
b00000000000000000000000000000011 '
b00000000000000000000000011111111 (
b11111111111111111111111100000100 )
b00000000000000000000000011111111 +
0,
0-
1.
b010 /
b001 0
b00110 2
b11001 3
b00000000000000000000000000000011 ?
b1100011 U
b001 V
b1111111 W
1X
#1575
0X
#1576
b00000000000000000000000000001100 $
b00000000000001011000010100010011 %
b00000000000000000000000000000000 &
b00000000000000000000000000000000 (
b00000000000000000000000000000011 )
b00000000000000000000000000000000 +
1,
1-
0.
b000 /
b000 0
b00000 2
b01010 3
b0010011 U
b000 V
b0000000 W
1X
#1577
0X
#1578
b00000000000000000000000000010000 $
b00000000000101011000010110010011 %
b00000000000000000000000000000001 &
b00000000000000000000000000000001 (
b00000000000000000000000000000100 )
b00001 2
b01011 3
b00000000000000000000000000000011 >
1X
b00000000000000000000000000000011 Z
#1579
0X
#1580
b00000000000000000000000000010100 $
b11111110011001011001110011100011 %
b11111111111111111111111111111000 &
b00000000000000000000000000000100 '
b00000000000000000000000011111111 (
b11111111111111111111111100000101 )
b00000000000000000000000011111111 +
0,
0-
1.
b010 /
b001 0
b00110 2
b11001 3
b00000000000000000000000000000100 ?
b1100011 U
b001 V
b1111111 W
1X
#1581
0X
#1582
b00000000000000000000000000001100 $
b00000000000001011000010100010011 %
b00000000000000000000000000000000 &
b00000000000000000000000000000000 (
b00000000000000000000000000000100 )
b00000000000000000000000000000000 +
1,
1-
0.
b000 /
b000 0
b00000 2
b01010 3
b0010011 U
b000 V
b0000000 W
1X
#1583
0X
#1584
b00000000000000000000000000010000 $
b00000000000101011000010110010011 %
b00000000000000000000000000000001 &
b00000000000000000000000000000001 (
b00000000000000000000000000000101 )
b00001 2
b01011 3
b00000000000000000000000000000100 >
1X
b00000000000000000000000000000100 Z
#1585
0X
#1586
b00000000000000000000000000010100 $
b11111110011001011001110011100011 %
b11111111111111111111111111111000 &
b00000000000000000000000000000101 '
b00000000000000000000000011111111 (
b11111111111111111111111100000110 )
b00000000000000000000000011111111 +
0,
0-
1.
b010 /
b001 0
b00110 2
b11001 3
b00000000000000000000000000000101 ?
b1100011 U
b001 V
b1111111 W
1X
#1587
0X
#1588
b00000000000000000000000000001100 $
b00000000000001011000010100010011 %
b00000000000000000000000000000000 &
b00000000000000000000000000000000 (
b00000000000000000000000000000101 )
b00000000000000000000000000000000 +
1,
1-
0.
b000 /
b000 0
b00000 2
b01010 3
b0010011 U
b000 V
b0000000 W
1X
#1589
0X
#1590
b00000000000000000000000000010000 $
b00000000000101011000010110010011 %
b00000000000000000000000000000001 &
b00000000000000000000000000000001 (
b00000000000000000000000000000110 )
b00001 2
b01011 3
b00000000000000000000000000000101 >
1X
b00000000000000000000000000000101 Z
#1591
0X
#1592
b00000000000000000000000000010100 $
b11111110011001011001110011100011 %
b11111111111111111111111111111000 &
b00000000000000000000000000000110 '
b00000000000000000000000011111111 (
b11111111111111111111111100000111 )
b00000000000000000000000011111111 +
0,
0-
1.
b010 /
b001 0
b00110 2
b11001 3
b00000000000000000000000000000110 ?
b1100011 U
b001 V
b1111111 W
1X
#1593
0X
#1594
b00000000000000000000000000001100 $
b00000000000001011000010100010011 %
b00000000000000000000000000000000 &
b00000000000000000000000000000000 (
b00000000000000000000000000000110 )
b00000000000000000000000000000000 +
1,
1-
0.
b000 /
b000 0
b00000 2
b01010 3
b0010011 U
b000 V
b0000000 W
1X
#1595
0X
#1596
b00000000000000000000000000010000 $
b00000000000101011000010110010011 %
b00000000000000000000000000000001 &
b00000000000000000000000000000001 (
b00000000000000000000000000000111 )
b00001 2
b01011 3
b00000000000000000000000000000110 >
1X
b00000000000000000000000000000110 Z
#1597
0X
#1598
b00000000000000000000000000010100 $
b11111110011001011001110011100011 %
b11111111111111111111111111111000 &
b00000000000000000000000000000111 '
b00000000000000000000000011111111 (
b11111111111111111111111100001000 )
b00000000000000000000000011111111 +
0,
0-
1.
b010 /
b001 0
b00110 2
b11001 3
b00000000000000000000000000000111 ?
b1100011 U
b001 V
b1111111 W
1X
#1599
0X
#1600
b00000000000000000000000000001100 $
b00000000000001011000010100010011 %
b00000000000000000000000000000000 &
b00000000000000000000000000000000 (
b00000000000000000000000000000111 )
b00000000000000000000000000000000 +
1,
1-
0.
b000 /
b000 0
b00000 2
b01010 3
b0010011 U
b000 V
b0000000 W
1X
#1601
0X
#1602
b00000000000000000000000000010000 $
b00000000000101011000010110010011 %
b00000000000000000000000000000001 &
b00000000000000000000000000000001 (
b00000000000000000000000000001000 )
b00001 2
b01011 3
b00000000000000000000000000000111 >
1X
b00000000000000000000000000000111 Z
#1603
0X
#1604
b00000000000000000000000000010100 $
b11111110011001011001110011100011 %
b11111111111111111111111111111000 &
b00000000000000000000000000001000 '
b00000000000000000000000011111111 (
b11111111111111111111111100001001 )
b00000000000000000000000011111111 +
0,
0-
1.
b010 /
b001 0
b00110 2
b11001 3
b00000000000000000000000000001000 ?
b1100011 U
b001 V
b1111111 W
1X
#1605
0X
#1606
b00000000000000000000000000001100 $
b00000000000001011000010100010011 %
b00000000000000000000000000000000 &
b00000000000000000000000000000000 (
b00000000000000000000000000001000 )
b00000000000000000000000000000000 +
1,
1-
0.
b000 /
b000 0
b00000 2
b01010 3
b0010011 U
b000 V
b0000000 W
1X
#1607
0X
#1608
b00000000000000000000000000010000 $
b00000000000101011000010110010011 %
b00000000000000000000000000000001 &
b00000000000000000000000000000001 (
b00000000000000000000000000001001 )
b00001 2
b01011 3
b00000000000000000000000000001000 >
1X
b00000000000000000000000000001000 Z
#1609
0X
#1610
b00000000000000000000000000010100 $
b11111110011001011001110011100011 %
b11111111111111111111111111111000 &
b00000000000000000000000000001001 '
b00000000000000000000000011111111 (
b11111111111111111111111100001010 )
b00000000000000000000000011111111 +
0,
0-
1.
b010 /
b001 0
b00110 2
b11001 3
b00000000000000000000000000001001 ?
b1100011 U
b001 V
b1111111 W
1X
#1611
0X
#1612
b00000000000000000000000000001100 $
b00000000000001011000010100010011 %
b00000000000000000000000000000000 &
b00000000000000000000000000000000 (
b00000000000000000000000000001001 )
b00000000000000000000000000000000 +
1,
1-
0.
b000 /
b000 0
b00000 2
b01010 3
b0010011 U
b000 V
b0000000 W
1X
#1613
0X
#1614
b00000000000000000000000000010000 $
b00000000000101011000010110010011 %
b00000000000000000000000000000001 &
b00000000000000000000000000000001 (
b00000000000000000000000000001010 )
b00001 2
b01011 3
b00000000000000000000000000001001 >
1X
b00000000000000000000000000001001 Z
#1615
0X
#1616
b00000000000000000000000000010100 $
b11111110011001011001110011100011 %
b11111111111111111111111111111000 &
b00000000000000000000000000001010 '
b00000000000000000000000011111111 (
b11111111111111111111111100001011 )
b00000000000000000000000011111111 +
0,
0-
1.
b010 /
b001 0
b00110 2
b11001 3
b00000000000000000000000000001010 ?
b1100011 U
b001 V
b1111111 W
1X
#1617
0X
#1618
b00000000000000000000000000001100 $
b00000000000001011000010100010011 %
b00000000000000000000000000000000 &
b00000000000000000000000000000000 (
b00000000000000000000000000001010 )
b00000000000000000000000000000000 +
1,
1-
0.
b000 /
b000 0
b00000 2
b01010 3
b0010011 U
b000 V
b0000000 W
1X
#1619
0X
#1620
b00000000000000000000000000010000 $
b00000000000101011000010110010011 %
b00000000000000000000000000000001 &
b00000000000000000000000000000001 (
b00000000000000000000000000001011 )
b00001 2
b01011 3
b00000000000000000000000000001010 >
1X
b00000000000000000000000000001010 Z
#1621
0X
#1622
b00000000000000000000000000010100 $
b11111110011001011001110011100011 %
b11111111111111111111111111111000 &
b00000000000000000000000000001011 '
b00000000000000000000000011111111 (
b11111111111111111111111100001100 )
b00000000000000000000000011111111 +
0,
0-
1.
b010 /
b001 0
b00110 2
b11001 3
b00000000000000000000000000001011 ?
b1100011 U
b001 V
b1111111 W
1X
#1623
0X
#1624
b00000000000000000000000000001100 $
b00000000000001011000010100010011 %
b00000000000000000000000000000000 &
b00000000000000000000000000000000 (
b00000000000000000000000000001011 )
b00000000000000000000000000000000 +
1,
1-
0.
b000 /
b000 0
b00000 2
b01010 3
b0010011 U
b000 V
b0000000 W
1X
#1625
0X
#1626
b00000000000000000000000000010000 $
b00000000000101011000010110010011 %
b00000000000000000000000000000001 &
b00000000000000000000000000000001 (
b00000000000000000000000000001100 )
b00001 2
b01011 3
b00000000000000000000000000001011 >
1X
b00000000000000000000000000001011 Z
#1627
0X
#1628
b00000000000000000000000000010100 $
b11111110011001011001110011100011 %
b11111111111111111111111111111000 &
b00000000000000000000000000001100 '
b00000000000000000000000011111111 (
b11111111111111111111111100001101 )
b00000000000000000000000011111111 +
0,
0-
1.
b010 /
b001 0
b00110 2
b11001 3
b00000000000000000000000000001100 ?
b1100011 U
b001 V
b1111111 W
1X
#1629
0X
#1630
b00000000000000000000000000001100 $
b00000000000001011000010100010011 %
b00000000000000000000000000000000 &
b00000000000000000000000000000000 (
b00000000000000000000000000001100 )
b00000000000000000000000000000000 +
1,
1-
0.
b000 /
b000 0
b00000 2
b01010 3
b0010011 U
b000 V
b0000000 W
1X
#1631
0X
#1632
b00000000000000000000000000010000 $
b00000000000101011000010110010011 %
b00000000000000000000000000000001 &
b00000000000000000000000000000001 (
b00000000000000000000000000001101 )
b00001 2
b01011 3
b00000000000000000000000000001100 >
1X
b00000000000000000000000000001100 Z
#1633
0X
#1634
b00000000000000000000000000010100 $
b11111110011001011001110011100011 %
b11111111111111111111111111111000 &
b00000000000000000000000000001101 '
b00000000000000000000000011111111 (
b11111111111111111111111100001110 )
b00000000000000000000000011111111 +
0,
0-
1.
b010 /
b001 0
b00110 2
b11001 3
b00000000000000000000000000001101 ?
b1100011 U
b001 V
b1111111 W
1X
#1635
0X
#1636
b00000000000000000000000000001100 $
b00000000000001011000010100010011 %
b00000000000000000000000000000000 &
b00000000000000000000000000000000 (
b00000000000000000000000000001101 )
b00000000000000000000000000000000 +
1,
1-
0.
b000 /
b000 0
b00000 2
b01010 3
b0010011 U
b000 V
b0000000 W
1X
#1637
0X
#1638
b00000000000000000000000000010000 $
b00000000000101011000010110010011 %
b00000000000000000000000000000001 &
b00000000000000000000000000000001 (
b00000000000000000000000000001110 )
b00001 2
b01011 3
b00000000000000000000000000001101 >
1X
b00000000000000000000000000001101 Z
#1639
0X
#1640
b00000000000000000000000000010100 $
b11111110011001011001110011100011 %
b11111111111111111111111111111000 &
b00000000000000000000000000001110 '
b00000000000000000000000011111111 (
b11111111111111111111111100001111 )
b00000000000000000000000011111111 +
0,
0-
1.
b010 /
b001 0
b00110 2
b11001 3
b00000000000000000000000000001110 ?
b1100011 U
b001 V
b1111111 W
1X
#1641
0X
#1642
b00000000000000000000000000001100 $
b00000000000001011000010100010011 %
b00000000000000000000000000000000 &
b00000000000000000000000000000000 (
b00000000000000000000000000001110 )
b00000000000000000000000000000000 +
1,
1-
0.
b000 /
b000 0
b00000 2
b01010 3
b0010011 U
b000 V
b0000000 W
1X
#1643
0X
